reqcurl/__init__.py
reqcurl/parser.py
reqcurl/wrapper.py
tests/__init__.py
tests/test_parser.py
tests/test_wrapper.py
reqcurl-0.1.1.dist-info/LICENSE
reqcurl-0.1.1.dist-info/METADATA
reqcurl-0.1.1.dist-info/WHEEL
reqcurl-0.1.1.dist-info/top_level.txt
reqcurl-0.1.1.dist-info/RECORD
