Metadata-Version: 2.1
Name: reqcurl
Version: 0.1.1
Summary: A Python wrapper for cURL commands to execute API requests.
Home-page: https://github.com/yourusername/reqcurl
Author: Sufiyan Ali Iqbal
Author-email: sufiyanaliiqbal@gmail.com
Classifier: Programming Language :: Python :: 3
Classifier: License :: OSI Approved :: MIT License
Classifier: Operating System :: OS Independent
Requires-Python: >=3.6
License-File: LICENSE
Requires-Dist: requests
